akmi_utils/__init__.py
akmi_utils/commons.py
akmi_utils/convert_toml_yaml.py
akmi_utils/logging.py
akmi_utils/models/__init__.py
akmi_utils/models/ras.py
akmi_utils/otel.py
akmi_utils-0.1.6.dist-info/LICENSE
akmi_utils-0.1.6.dist-info/METADATA
akmi_utils-0.1.6.dist-info/WHEEL
akmi_utils-0.1.6.dist-info/RECORD
