Metadata-Version: 2.3
Name: akmi-utils
Version: 0.1.6
Summary: 
Author: Eko Indarto
Author-email: eko.indarto@dans.knaw.nl
Requires-Python: >=3.12.8,<4.0.0
Classifier: Programming Language :: Python :: 3
Classifier: Programming Language :: Python :: 3.13
Requires-Dist: fastapi (>=0.115.7,<0.116.0)
Requires-Dist: httpx (>=0.28.1,<0.29.0)
Requires-Dist: opentelemetry-distro (>=0.50b0,<0.51)
Requires-Dist: opentelemetry-exporter-otlp (>=1.29.0,<2.0.0)
Requires-Dist: opentelemetry-instrumentation-fastapi (>=0.50b0,<0.51)
Requires-Dist: opentelemetry-instrumentation-logging (>=0.50b0,<0.51)
Requires-Dist: prometheus-client (>=0.21.1,<0.22.0)
Requires-Dist: pyyaml (>=6.0.2,<7.0.0)
Requires-Dist: toml (>=0.10.2,<0.11.0)
Requires-Dist: tomli (>=2.2.1,<3.0.0)
Requires-Dist: uvicorn (>=0.34.0,<0.35.0)
